pyhttp/__init__.py
pyhttp/__main__.py
pyhttp/templates/404.html
pyhttp/templates/favicon.ico
pyhttp/templates/index.html
foyou_http-0.0.16.dist-info/LICENSE
foyou_http-0.0.16.dist-info/METADATA
foyou_http-0.0.16.dist-info/WHEEL
foyou_http-0.0.16.dist-info/entry_points.txt
foyou_http-0.0.16.dist-info/top_level.txt
foyou_http-0.0.16.dist-info/RECORD
