Metadata-Version: 2.1
Name: foyou-http
Version: 0.0.16
Summary: simple http server for share files.
Author: foyoux
Project-URL: Source, https://github.com/foyoux/foyou-http
Project-URL: Homepage, https://github.com/foyoux/foyou-http
Project-URL: Bug Tracker, https://github.com/foyoux/foyou-http/issues
Keywords: foyou-http
Classifier: Programming Language :: Python
Classifier: Programming Language :: Python :: 3
Classifier: Programming Language :: Python :: 3.7
Classifier: Programming Language :: Python :: 3.8
Classifier: Programming Language :: Python :: 3.9
Classifier: Programming Language :: Python :: 3.10
Classifier: Programming Language :: Python :: 3.11
Requires-Python: >=3.7
License-File: LICENSE
Requires-Dist: flask
Requires-Dist: werkzeug
Requires-Dist: flask-cors
